jupyter_ascending/__init__.py
jupyter_ascending/_environment.py
jupyter_ascending/_frontend.py
jupyter_ascending/_version.py
jupyter_ascending/errors.py
jupyter_ascending/extension.py
jupyter_ascending/functional.py
jupyter_ascending/handlers/__init__.py
jupyter_ascending/handlers/jupyter_notebook.py
jupyter_ascending/handlers/server_extension.py
jupyter_ascending/json_requests.py
jupyter_ascending/labextension/jupyter_ascending-0.1.0.tgz
jupyter_ascending/logger.py
jupyter_ascending/nbextension/__init__.py
jupyter_ascending/nbextension/static/extension.js
jupyter_ascending/nbextension/static/index.js
jupyter_ascending/nbextension/static/index.js.map
jupyter_ascending/notebook/__init__.py
jupyter_ascending/notebook/data_types.py
jupyter_ascending/notebook/evolve.py
jupyter_ascending/notebook/merge.py
jupyter_ascending/requests/__init__.py
jupyter_ascending/requests/client_lib.py
jupyter_ascending/requests/execute.py
jupyter_ascending/requests/execute_all.py
jupyter_ascending/requests/get_status.py
jupyter_ascending/requests/readme.md
jupyter_ascending/requests/restart.py
jupyter_ascending/requests/sync.py
jupyter_ascending/scripts/make_pair.py
jupyter_ascending/tests/__init__.py
jupyter_ascending/tests/test_cell_matching.py
jupyter_ascending/tests/test_execute_request.py
jupyter_ascending/tests/test_nbextension_path.py
jupyter_ascending/tests/test_notebook_matching.py
jupyter_ascending/utils.py
jupyter_ascending_patched-0.1.23.1.dist-info/entry_points.txt
jupyter_ascending_patched-0.1.23.1.dist-info/LICENSE
jupyter_ascending_patched-0.1.23.1.dist-info/WHEEL
jupyter_ascending_patched-0.1.23.1.dist-info/METADATA
jupyter_ascending_patched-0.1.23.1.dist-info/RECORD
