Metadata-Version: 2.1
Name: jupyter-ascending-patched
Version: 0.1.23.1
Summary: 
Author: Josh Albrecht
Author-email: joshalbrecht@gmail.com
Requires-Python: >=3.6,<4.0
Classifier: Programming Language :: Python :: 3
Classifier: Programming Language :: Python :: 3.10
Classifier: Programming Language :: Python :: 3.6
Classifier: Programming Language :: Python :: 3.7
Classifier: Programming Language :: Python :: 3.8
Classifier: Programming Language :: Python :: 3.9
Requires-Dist: attrs (>=19.0.0)
Requires-Dist: edlib (>=1.3.8,<2.0.0)
Requires-Dist: ipywidgets (>=7.5.1,<8.0.0)
Requires-Dist: jsonrpcclient[requests] (>=3.3.5,<4.0.0)
Requires-Dist: jsonrpcserver[requests] (>=4.1.2,<5.0.0)
Requires-Dist: jupytext (>=1.3.4,<2.0.0)
Requires-Dist: loguru (>=0.4.1)
Requires-Dist: toml (>=0.10.0)
